xylose/__init__.py
xylose/choices.py
xylose/iso3166.py
xylose/scielodocument.py
xylose/tools.py
xylose/assets/__init__.py
xylose/assets/country_codes.csv
xylose-1.33.2.dist-info/METADATA
xylose-1.33.2.dist-info/RECORD
xylose-1.33.2.dist-info/WHEEL
xylose-1.33.2.dist-info/top_level.txt
