Metadata-Version: 2.1
Name: xylose
Version: 1.33.2
Summary: A SciELO library to abstract a JSON data structure that is a product of the ISIS2JSON conversion using the ISIS2JSON type 3 data model.
Home-page: http://docs.scielo.org
Author: SciELO
Author-email: scielo-dev@googlegroups.com
License: BSD 2-clause
Platform: UNKNOWN
Classifier: Development Status :: 1 - Planning
Classifier: Intended Audience :: Customer Service
Classifier: License :: OSI Approved :: BSD License
Classifier: Programming Language :: Python
Classifier: Operating System :: POSIX :: Linux
Classifier: Topic :: System
Classifier: Topic :: Utilities
Requires-Dist: legendarium (>=1.2.0)
